pmcplume/__init__.py
pmcplume/pmcplume_server.py
pmcplume/pubmed_client.py
pmcplume-0.1.0.dist-info/METADATA
pmcplume-0.1.0.dist-info/WHEEL
pmcplume-0.1.0.dist-info/entry_points.txt
pmcplume-0.1.0.dist-info/RECORD
