Metadata-Version: 2.4
Name: pmcplume
Version: 0.1.0
Summary: A lightweight MCP server for PubMed queries
Author-email: yxt <15122150377@163.com>
Requires-Python: >=3.10
Requires-Dist: httpx>=0.27.0
Requires-Dist: mcp<2,>=1.0.0
Requires-Dist: pydantic>=2.0.0
